{
    "data": [
        [
            {
                "team": {
                    "id": 234,
                    "name": "Pacos Ferreira",
                    "code": "FER",
                    "country": "Portugal",
                    "founded": 1950,
                    "national": false,
                    "logo": "https://media-2.api-sports.io/football/teams/234.png"
                },
                "venue": {
                    "id": 1283,
                    "name": "Est\u00e1dio da Capital do M\u00f3vel",
                    "address": "Rua do Est\u00e1dio, Apartado 26",
                    "city": "Pa\u00e7os de Ferreira",
                    "capacity": 9146,
                    "surface": "grass",
                    "image": "https://media-3.api-sports.io/football/venues/1283.png"
                }
            }
        ]
    ]
}