{
    "data": [
        [
            {
                "team": {
                    "id": 453,
                    "name": "Independiente",
                    "code": "IND",
                    "country": "Argentina",
                    "founded": 1905,
                    "national": false,
                    "logo": "https://media-1.api-sports.io/football/teams/453.png"
                },
                "venue": {
                    "id": 7131,
                    "name": "Estadio Libertadores de Am\u00e9rica",
                    "address": "Calle Ricardo Enrique Bochini 751/83 esq. Alsina",
                    "city": "Avellaneda, Provincia de Buenos Aires",
                    "capacity": 52364,
                    "surface": "grass",
                    "image": "https://media-2.api-sports.io/football/venues/7131.png"
                }
            }
        ]
    ]
}