{
    "data": [
        [
            {
                "team": {
                    "id": 14002,
                    "name": "Mazatl\u00e1n",
                    "logo": "https://media-3.api-sports.io/football/teams/14002.png"
                },
                "players": [
                    {
                        "id": 35929,
                        "name": "R. Guti\u00e9rrez",
                        "age": 26,
                        "number": 1,
                        "position": "Goalkeeper",
                        "photo": "https://media-3.api-sports.io/football/players/35929.png"
                    },
                    {
                        "id": 35734,
                        "name": "N. Vikonis",
                        "age": 39,
                        "number": 27,
                        "position": "Goalkeeper",
                        "photo": "https://media-1.api-sports.io/football/players/35734.png"
                    },
                    {
                        "id": 282709,
                        "name": "R. Rodr\u00edguez",
                        "age": 22,
                        "number": 30,
                        "position": "Goalkeeper",
                        "photo": "https://media-3.api-sports.io/football/players/282709.png"
                    },
                    {
                        "id": 35745,
                        "name": "N. Vidrio",
                        "age": 34,
                        "number": 3,
                        "position": "Defender",
                        "photo": "https://media-1.api-sports.io/football/players/35745.png"
                    },
                    {
                        "id": 6494,
                        "name": "F. Almada",
                        "age": 25,
                        "number": 5,
                        "position": "Defender",
                        "photo": "https://media-3.api-sports.io/football/players/6494.png"
                    },
                    {
                        "id": 46844,
                        "name": "O. Alan\u00eds",
                        "age": 34,
                        "number": 14,
                        "position": "Defender",
                        "photo": "https://media-3.api-sports.io/football/players/46844.png"
                    },
                    {
                        "id": 36195,
                        "name": "B. Colula",
                        "age": 27,
                        "number": 15,
                        "position": "Defender",
                        "photo": "https://media-2.api-sports.io/football/players/36195.png"
                    },
                    {
                        "id": 35517,
                        "name": "F. Venegas",
                        "age": 25,
                        "number": 17,
                        "position": "Defender",
                        "photo": "https://media-3.api-sports.io/football/players/35517.png"
                    },
                    {
                        "id": 95468,
                        "name": "E. Cedillo",
                        "age": 27,
                        "number": 18,
                        "position": "Defender",
                        "photo": "https://media-3.api-sports.io/football/players/95468.png"
                    },
                    {
                        "id": 36166,
                        "name": "R. Sandoval",
                        "age": 23,
                        "number": 19,
                        "position": "Defender",
                        "photo": "https://media-2.api-sports.io/football/players/36166.png"
                    },
                    {
                        "id": 35909,
                        "name": "L. Quintana",
                        "age": 31,
                        "number": 20,
                        "position": "Defender",
                        "photo": "https://media-2.api-sports.io/football/players/35909.png"
                    },
                    {
                        "id": 36330,
                        "name": "J. Padilla",
                        "age": 30,
                        "number": 28,
                        "position": "Defender",
                        "photo": "https://media-3.api-sports.io/football/players/36330.png"
                    },
                    {
                        "id": 35663,
                        "name": "E. Orona",
                        "age": 24,
                        "number": 4,
                        "position": "Midfielder",
                        "photo": "https://media-3.api-sports.io/football/players/35663.png"
                    },
                    {
                        "id": 35943,
                        "name": "R. Meraz",
                        "age": 24,
                        "number": 6,
                        "position": "Midfielder",
                        "photo": "https://media-1.api-sports.io/football/players/35943.png"
                    },
                    {
                        "id": 50932,
                        "name": "J. Colm\u00e1n",
                        "age": 25,
                        "number": 8,
                        "position": "Midfielder",
                        "photo": "https://media-2.api-sports.io/football/players/50932.png"
                    },
                    {
                        "id": 50741,
                        "name": "M. Fabi\u00e1n",
                        "age": 34,
                        "number": 11,
                        "position": "Midfielder",
                        "photo": "https://media-1.api-sports.io/football/players/50741.png"
                    },
                    {
                        "id": 11765,
                        "name": "E. Bello",
                        "age": 28,
                        "number": 21,
                        "position": "Midfielder",
                        "photo": "https://media-3.api-sports.io/football/players/11765.png"
                    },
                    {
                        "id": 357997,
                        "name": "A. Monta\u00f1o",
                        "age": 21,
                        "number": 22,
                        "position": "Midfielder",
                        "photo": "https://media-3.api-sports.io/football/players/357997.png"
                    },
                    {
                        "id": 35625,
                        "name": "F. Illescas",
                        "age": 24,
                        "number": 29,
                        "position": "Midfielder",
                        "photo": "https://media-1.api-sports.io/football/players/35625.png"
                    },
                    {
                        "id": 2579,
                        "name": "J. Intriago",
                        "age": 27,
                        "number": 35,
                        "position": "Midfielder",
                        "photo": "https://media-1.api-sports.io/football/players/2579.png"
                    },
                    {
                        "id": 405999,
                        "name": "J. Guti\u00e9rrez",
                        "age": 20,
                        "number": 182,
                        "position": "Midfielder",
                        "photo": "https://media-3.api-sports.io/football/players/405999.png"
                    },
                    {
                        "id": 416198,
                        "name": "G. Adame",
                        "age": 19,
                        "number": 200,
                        "position": "Midfielder",
                        "photo": "https://media-3.api-sports.io/football/players/416198.png"
                    },
                    {
                        "id": 405998,
                        "name": "I. Mu\u00f1oz",
                        "age": 21,
                        "number": 205,
                        "position": "Midfielder",
                        "photo": "https://media-2.api-sports.io/football/players/405998.png"
                    },
                    {
                        "id": 46855,
                        "name": "Y. B\u00e1rcenas",
                        "age": 30,
                        "number": 7,
                        "position": "Attacker",
                        "photo": "https://media-2.api-sports.io/football/players/46855.png"
                    },
                    {
                        "id": 35988,
                        "name": "A. Loba",
                        "age": 25,
                        "number": 9,
                        "position": "Attacker",
                        "photo": "https://media-3.api-sports.io/football/players/35988.png"
                    },
                    {
                        "id": 35589,
                        "name": "N. Benedetti",
                        "age": 26,
                        "number": 10,
                        "position": "Attacker",
                        "photo": "https://media-3.api-sports.io/football/players/35589.png"
                    },
                    {
                        "id": 36251,
                        "name": "E. S\u00e1nchez",
                        "age": 29,
                        "number": 16,
                        "position": "Attacker",
                        "photo": "https://media-1.api-sports.io/football/players/36251.png"
                    },
                    {
                        "id": 35958,
                        "name": "M. Sansores",
                        "age": 32,
                        "number": 25,
                        "position": "Attacker",
                        "photo": "https://media-2.api-sports.io/football/players/35958.png"
                    },
                    {
                        "id": 35700,
                        "name": "A. Nahuelp\u00e1n",
                        "age": 36,
                        "number": 32,
                        "position": "Attacker",
                        "photo": "https://media-2.api-sports.io/football/players/35700.png"
                    },
                    {
                        "id": 372587,
                        "name": "R. Camacho",
                        "age": 21,
                        "number": 34,
                        "position": "Attacker",
                        "photo": "https://media-2.api-sports.io/football/players/372587.png"
                    },
                    {
                        "id": 403700,
                        "name": "O. Moreno",
                        "age": 18,
                        "number": 184,
                        "position": "Attacker",
                        "photo": "https://media-2.api-sports.io/football/players/403700.png"
                    },
                    {
                        "id": 372171,
                        "name": "G. L\u00f3pez",
                        "age": 20,
                        "number": 193,
                        "position": "Attacker",
                        "photo": "https://media-2.api-sports.io/football/players/372171.png"
                    },
                    {
                        "id": 413060,
                        "name": "R. \u00c1rciga",
                        "age": 19,
                        "number": 208,
                        "position": "Attacker",
                        "photo": "https://media-1.api-sports.io/football/players/413060.png"
                    }
                ]
            }
        ]
    ]
}