{
    "data": [
        [
            {
                "team": {
                    "id": 228,
                    "name": "Sporting CP",
                    "logo": "https://media-1.api-sports.io/football/teams/228.png"
                },
                "players": [
                    {
                        "id": 27,
                        "name": "Ad\u00e1n",
                        "age": 36,
                        "number": 1,
                        "position": "Goalkeeper",
                        "photo": "https://media-1.api-sports.io/football/players/27.png"
                    },
                    {
                        "id": 56266,
                        "name": "F. Israel",
                        "age": 23,
                        "number": 12,
                        "position": "Goalkeeper",
                        "photo": "https://media-2.api-sports.io/football/players/56266.png"
                    },
                    {
                        "id": 142411,
                        "name": "Andr\u00e9 Paulo",
                        "age": 27,
                        "number": 22,
                        "position": "Goalkeeper",
                        "photo": "https://media-3.api-sports.io/football/players/142411.png"
                    },
                    {
                        "id": 330296,
                        "name": "Diego Callai",
                        "age": 19,
                        "number": 41,
                        "position": "Goalkeeper",
                        "photo": "https://media-1.api-sports.io/football/players/330296.png"
                    },
                    {
                        "id": 361417,
                        "name": "Francisco Silva",
                        "age": 18,
                        "number": 99,
                        "position": "Goalkeeper",
                        "photo": "https://media-3.api-sports.io/football/players/361417.png"
                    },
                    {
                        "id": 336676,
                        "name": "Diogo Pinto",
                        "age": 19,
                        "number": null,
                        "position": "Goalkeeper",
                        "photo": "https://media-1.api-sports.io/football/players/336676.png"
                    },
                    {
                        "id": 41179,
                        "name": "Matheus Reis",
                        "age": 28,
                        "number": 2,
                        "position": "Defender",
                        "photo": "https://media-1.api-sports.io/football/players/41179.png"
                    },
                    {
                        "id": 37148,
                        "name": "J. St. Juste",
                        "age": 27,
                        "number": 3,
                        "position": "Defender",
                        "photo": "https://media-3.api-sports.io/football/players/37148.png"
                    },
                    {
                        "id": 1477,
                        "name": "S. Coates",
                        "age": 33,
                        "number": 4,
                        "position": "Defender",
                        "photo": "https://media-2.api-sports.io/football/players/1477.png"
                    },
                    {
                        "id": 1203,
                        "name": "Lu\u00eds Carlos",
                        "age": 35,
                        "number": 13,
                        "position": "Defender",
                        "photo": "https://media-3.api-sports.io/football/players/1203.png"
                    },
                    {
                        "id": 1439,
                        "name": "H\u00e9ctor Beller\u00edn",
                        "age": 28,
                        "number": 19,
                        "position": "Defender",
                        "photo": "https://media-1.api-sports.io/football/players/1439.png"
                    },
                    {
                        "id": 265595,
                        "name": "Gon\u00e7alo In\u00e1cio",
                        "age": 22,
                        "number": 25,
                        "position": "Defender",
                        "photo": "https://media-1.api-sports.io/football/players/265595.png"
                    },
                    {
                        "id": 354753,
                        "name": "O. Diomande",
                        "age": 20,
                        "number": 26,
                        "position": "Defender",
                        "photo": "https://media-1.api-sports.io/football/players/354753.png"
                    },
                    {
                        "id": 41099,
                        "name": "Ricardo Esgaio",
                        "age": 30,
                        "number": 47,
                        "position": "Defender",
                        "photo": "https://media-2.api-sports.io/football/players/41099.png"
                    },
                    {
                        "id": 294722,
                        "name": "Fl\u00e1vio Nazinho",
                        "age": 20,
                        "number": 71,
                        "position": "Defender",
                        "photo": "https://media-3.api-sports.io/football/players/294722.png"
                    },
                    {
                        "id": 281438,
                        "name": "Chico Lamba",
                        "age": 20,
                        "number": 73,
                        "position": "Defender",
                        "photo": "https://media-1.api-sports.io/football/players/281438.png"
                    },
                    {
                        "id": 336575,
                        "name": "Diogo Travassos",
                        "age": 19,
                        "number": 97,
                        "position": "Defender",
                        "photo": "https://media-3.api-sports.io/football/players/336575.png"
                    },
                    {
                        "id": 325052,
                        "name": "Gon\u00e7alo Esteves",
                        "age": 19,
                        "number": null,
                        "position": "Defender",
                        "photo": "https://media-2.api-sports.io/football/players/325052.png"
                    },
                    {
                        "id": 32960,
                        "name": "H. Morita",
                        "age": 28,
                        "number": 5,
                        "position": "Midfielder",
                        "photo": "https://media-3.api-sports.io/football/players/32960.png"
                    },
                    {
                        "id": 135842,
                        "name": "S. Alexandropoulos",
                        "age": 22,
                        "number": 6,
                        "position": "Midfielder",
                        "photo": "https://media-2.api-sports.io/football/players/135842.png"
                    },
                    {
                        "id": 41194,
                        "name": "Nuno Santos",
                        "age": 28,
                        "number": 11,
                        "position": "Midfielder",
                        "photo": "https://media-2.api-sports.io/football/players/41194.png"
                    },
                    {
                        "id": 51494,
                        "name": "M. Ugarte",
                        "age": 22,
                        "number": 15,
                        "position": "Midfielder",
                        "photo": "https://media-2.api-sports.io/football/players/51494.png"
                    },
                    {
                        "id": 41892,
                        "name": "Daniel Bragan\u00e7a",
                        "age": 24,
                        "number": 23,
                        "position": "Midfielder",
                        "photo": "https://media-2.api-sports.io/football/players/41892.png"
                    },
                    {
                        "id": 18748,
                        "name": "Pote",
                        "age": 25,
                        "number": 28,
                        "position": "Midfielder",
                        "photo": "https://media-2.api-sports.io/football/players/18748.png"
                    },
                    {
                        "id": 289445,
                        "name": "M. Tanlongo",
                        "age": 20,
                        "number": 32,
                        "position": "Midfielder",
                        "photo": "https://media-1.api-sports.io/football/players/289445.png"
                    },
                    {
                        "id": 10006,
                        "name": "Arthur Gomes",
                        "age": 25,
                        "number": 33,
                        "position": "Midfielder",
                        "photo": "https://media-1.api-sports.io/football/players/10006.png"
                    },
                    {
                        "id": 336585,
                        "name": "Mateus Fernandes",
                        "age": 19,
                        "number": 82,
                        "position": "Midfielder",
                        "photo": "https://media-2.api-sports.io/football/players/336585.png"
                    },
                    {
                        "id": 308678,
                        "name": "D\u00e1rio Essugo",
                        "age": 18,
                        "number": 84,
                        "position": "Midfielder",
                        "photo": "https://media-2.api-sports.io/football/players/308678.png"
                    },
                    {
                        "id": 37882,
                        "name": "M. Edwards",
                        "age": 25,
                        "number": 10,
                        "position": "Attacker",
                        "photo": "https://media-1.api-sports.io/football/players/37882.png"
                    },
                    {
                        "id": 41154,
                        "name": "Rochinha",
                        "age": 28,
                        "number": 16,
                        "position": "Attacker",
                        "photo": "https://media-3.api-sports.io/football/players/41154.png"
                    },
                    {
                        "id": 41112,
                        "name": "Trinc\u00e3o",
                        "age": 24,
                        "number": 17,
                        "position": "Attacker",
                        "photo": "https://media-1.api-sports.io/football/players/41112.png"
                    },
                    {
                        "id": 303467,
                        "name": "I. Fatawu",
                        "age": 19,
                        "number": 18,
                        "position": "Attacker",
                        "photo": "https://media-1.api-sports.io/football/players/303467.png"
                    },
                    {
                        "id": 41111,
                        "name": "Paulinho",
                        "age": 31,
                        "number": 20,
                        "position": "Attacker",
                        "photo": "https://media-3.api-sports.io/football/players/41111.png"
                    },
                    {
                        "id": 1494,
                        "name": "Jovane Cabral",
                        "age": 25,
                        "number": 77,
                        "position": "Attacker",
                        "photo": "https://media-2.api-sports.io/football/players/1494.png"
                    },
                    {
                        "id": 330412,
                        "name": "Youssef Chermiti",
                        "age": 19,
                        "number": 79,
                        "position": "Attacker",
                        "photo": "https://media-1.api-sports.io/football/players/330412.png"
                    },
                    {
                        "id": 341641,
                        "name": "Rodrigo Ribeiro",
                        "age": 18,
                        "number": 91,
                        "position": "Attacker",
                        "photo": "https://media-1.api-sports.io/football/players/341641.png"
                    },
                    {
                        "id": 345388,
                        "name": "Afonso Moreira",
                        "age": 18,
                        "number": 98,
                        "position": "Attacker",
                        "photo": "https://media-2.api-sports.io/football/players/345388.png"
                    }
                ]
            }
        ]
    ]
}