{
    "data": [
        [
            {
                "team": {
                    "id": 724,
                    "name": "Cadiz",
                    "logo": "https://media-3.api-sports.io/football/teams/724.png"
                },
                "players": [
                    {
                        "id": 6492,
                        "name": "J. Ledesma",
                        "age": 30,
                        "number": 1,
                        "position": "Goalkeeper",
                        "photo": "https://media-2.api-sports.io/football/players/6492.png"
                    },
                    {
                        "id": 46755,
                        "name": "David Gil",
                        "age": 29,
                        "number": 13,
                        "position": "Goalkeeper",
                        "photo": "https://media-3.api-sports.io/football/players/46755.png"
                    },
                    {
                        "id": 337963,
                        "name": "Victor Aznar",
                        "age": 21,
                        "number": 26,
                        "position": "Goalkeeper",
                        "photo": "https://media-2.api-sports.io/football/players/337963.png"
                    },
                    {
                        "id": 185810,
                        "name": "Ra\u00fal Parra",
                        "age": 24,
                        "number": 2,
                        "position": "Defender",
                        "photo": "https://media-2.api-sports.io/football/players/185810.png"
                    },
                    {
                        "id": 47229,
                        "name": "Fali",
                        "age": 30,
                        "number": 3,
                        "position": "Defender",
                        "photo": "https://media-2.api-sports.io/football/players/47229.png"
                    },
                    {
                        "id": 14444,
                        "name": "M. Mbaye",
                        "age": 25,
                        "number": 5,
                        "position": "Defender",
                        "photo": "https://media-3.api-sports.io/football/players/14444.png"
                    },
                    {
                        "id": 47100,
                        "name": "Iza Carcel\u00e9n",
                        "age": 30,
                        "number": 20,
                        "position": "Defender",
                        "photo": "https://media-2.api-sports.io/football/players/47100.png"
                    },
                    {
                        "id": 2508,
                        "name": "S. Arzamendia",
                        "age": 25,
                        "number": 21,
                        "position": "Defender",
                        "photo": "https://media-2.api-sports.io/football/players/2508.png"
                    },
                    {
                        "id": 46759,
                        "name": "A. Espino",
                        "age": 31,
                        "number": 22,
                        "position": "Defender",
                        "photo": "https://media-3.api-sports.io/football/players/46759.png"
                    },
                    {
                        "id": 46818,
                        "name": "Luis Hern\u00e1ndez",
                        "age": 34,
                        "number": 23,
                        "position": "Defender",
                        "photo": "https://media-3.api-sports.io/football/players/46818.png"
                    },
                    {
                        "id": 24793,
                        "name": "Jorge Mer\u00e9",
                        "age": 26,
                        "number": 25,
                        "position": "Defender",
                        "photo": "https://media-2.api-sports.io/football/players/24793.png"
                    },
                    {
                        "id": 144261,
                        "name": "Carlos Garc\u00eda-Die",
                        "age": 23,
                        "number": 30,
                        "position": "Defender",
                        "photo": "https://media-3.api-sports.io/football/players/144261.png"
                    },
                    {
                        "id": 162058,
                        "name": "V\u00edctor Chust",
                        "age": 23,
                        "number": 32,
                        "position": "Defender",
                        "photo": "https://media-2.api-sports.io/football/players/162058.png"
                    },
                    {
                        "id": 181211,
                        "name": "Genar Forn\u00e9s",
                        "age": 23,
                        "number": null,
                        "position": "Defender",
                        "photo": "https://media-1.api-sports.io/football/players/181211.png"
                    },
                    {
                        "id": 46998,
                        "name": "Juan Cala",
                        "age": 34,
                        "number": null,
                        "position": "Defender",
                        "photo": "https://media-3.api-sports.io/football/players/46998.png"
                    },
                    {
                        "id": 47307,
                        "name": "Joseba Zald\u00faa",
                        "age": 31,
                        "number": null,
                        "position": "Defender",
                        "photo": "https://media-2.api-sports.io/football/players/47307.png"
                    },
                    {
                        "id": 47485,
                        "name": "Rub\u00e9n Alcaraz",
                        "age": 32,
                        "number": 4,
                        "position": "Midfielder",
                        "photo": "https://media-1.api-sports.io/football/players/47485.png"
                    },
                    {
                        "id": 46772,
                        "name": "Jos\u00e9 Mari",
                        "age": 36,
                        "number": 6,
                        "position": "Midfielder",
                        "photo": "https://media-2.api-sports.io/football/players/46772.png"
                    },
                    {
                        "id": 46769,
                        "name": "\u00c1lex Fern\u00e1ndez",
                        "age": 31,
                        "number": 8,
                        "position": "Midfielder",
                        "photo": "https://media-1.api-sports.io/football/players/46769.png"
                    },
                    {
                        "id": 46824,
                        "name": "Iv\u00e1n Alejo",
                        "age": 28,
                        "number": 11,
                        "position": "Midfielder",
                        "photo": "https://media-1.api-sports.io/football/players/46824.png"
                    },
                    {
                        "id": 77623,
                        "name": "Y. Diarra",
                        "age": 25,
                        "number": 12,
                        "position": "Midfielder",
                        "photo": "https://media-1.api-sports.io/football/players/77623.png"
                    },
                    {
                        "id": 47388,
                        "name": "G. Escalante",
                        "age": 30,
                        "number": 17,
                        "position": "Midfielder",
                        "photo": "https://media-1.api-sports.io/football/players/47388.png"
                    },
                    {
                        "id": 46691,
                        "name": "Fede San Emeterio",
                        "age": 26,
                        "number": 24,
                        "position": "Midfielder",
                        "photo": "https://media-2.api-sports.io/football/players/46691.png"
                    },
                    {
                        "id": 310683,
                        "name": "\u00c1lvaro Bastida",
                        "age": 19,
                        "number": 38,
                        "position": "Midfielder",
                        "photo": "https://media-3.api-sports.io/football/players/310683.png"
                    },
                    {
                        "id": 937,
                        "name": "Rub\u00e9n Sobrino",
                        "age": 31,
                        "number": 7,
                        "position": "Attacker",
                        "photo": "https://media-1.api-sports.io/football/players/937.png"
                    },
                    {
                        "id": 47525,
                        "name": "A. Lozano",
                        "age": 30,
                        "number": 9,
                        "position": "Attacker",
                        "photo": "https://media-2.api-sports.io/football/players/47525.png"
                    },
                    {
                        "id": 8627,
                        "name": "T. Bongonda",
                        "age": 28,
                        "number": 10,
                        "position": "Attacker",
                        "photo": "https://media-1.api-sports.io/football/players/8627.png"
                    },
                    {
                        "id": 51588,
                        "name": "B. Ocampo",
                        "age": 24,
                        "number": 14,
                        "position": "Attacker",
                        "photo": "https://media-2.api-sports.io/football/players/51588.png"
                    },
                    {
                        "id": 47471,
                        "name": "Roger",
                        "age": 32,
                        "number": 15,
                        "position": "Attacker",
                        "photo": "https://media-2.api-sports.io/football/players/47471.png"
                    },
                    {
                        "id": 104792,
                        "name": "Chris Ramos",
                        "age": 26,
                        "number": 16,
                        "position": "Attacker",
                        "photo": "https://media-3.api-sports.io/football/players/104792.png"
                    },
                    {
                        "id": 50502,
                        "name": "\u00c1lvaro Negredo",
                        "age": 38,
                        "number": 18,
                        "position": "Attacker",
                        "photo": "https://media-3.api-sports.io/football/players/50502.png"
                    },
                    {
                        "id": 47495,
                        "name": "Sergi Guardiola",
                        "age": 32,
                        "number": 19,
                        "position": "Attacker",
                        "photo": "https://media-3.api-sports.io/football/players/47495.png"
                    },
                    {
                        "id": 182759,
                        "name": "M. Diarra",
                        "age": 23,
                        "number": 29,
                        "position": "Attacker",
                        "photo": "https://media-3.api-sports.io/football/players/182759.png"
                    }
                ]
            }
        ]
    ]
}